patman/__init__.py
patman/main.py
patman/utils.py
patman-0.0.6.dist-info/DESCRIPTION.rst
patman-0.0.6.dist-info/METADATA
patman-0.0.6.dist-info/RECORD
patman-0.0.6.dist-info/WHEEL
patman-0.0.6.dist-info/metadata.json
patman-0.0.6.dist-info/top_level.txt
